flowerpot.py
flowerpot-0.0.2.dist-info/LICENSE
flowerpot-0.0.2.dist-info/WHEEL
flowerpot-0.0.2.dist-info/METADATA
flowerpot-0.0.2.dist-info/RECORD
