Metadata-Version: 2.1
Name: flowerpot
Version: 0.0.2
Summary: Displays flower ASCII art
Author-email: Pavithra Eswaramoorthy <hi@pavithraes.me>
Project-URL: Home, https://github.com/pavithraes/flowerpot
